propertymapper/__init__.py
propertymapper/mapper.py
pymapper-0.1.0.dist-info/LICENSE
pymapper-0.1.0.dist-info/METADATA
pymapper-0.1.0.dist-info/WHEEL
pymapper-0.1.0.dist-info/top_level.txt
pymapper-0.1.0.dist-info/RECORD
