Metadata-Version: 2.1
Name: pymapper
Version: 0.1.0
Summary: provide toDict method for subclasses 
Home-page: https://github.com/alburthoffman/pymapper
Author: Alburt Hoffman
Author-email: hoffmantang@yahoo.com
License: MIT
Platform: UNKNOWN
